{"timestamp":"2017-05-29 14:02:43",
 "type":"gallery",
 "title":"Amsterdam 2017",
 "slug":"amsterdam-2017",
 "text":"Da Vinci and Het Rijksmuseum. We do culture good.",
 "photos":
[{"name":"amsterdam-2017-001", "size":[3229, 4535]}
,{"name":"amsterdam-2017-002", "size":[3414, 5122]}
,{"name":"amsterdam-2017-003", "size":[5184, 3456]}
,{"name":"amsterdam-2017-004", "size":[5083, 3092]}
,{"name":"amsterdam-2017-005", "size":[4500, 3145]}
,{"name":"amsterdam-2017-006", "size":[3262, 3743]}
,{"name":"amsterdam-2017-007", "size":[5065, 3376]}
,{"name":"amsterdam-2017-008", "size":[4283, 2642]}
,{"name":"amsterdam-2017-009", "size":[4867, 3345]}
,{"name":"amsterdam-2017-010", "size":[5122, 3414]}
,{"name":"amsterdam-2017-011", "size":[3778, 3346]}
,{"name":"amsterdam-2017-012", "size":[4796, 3172]}
,{"name":"amsterdam-2017-013", "size":[4783, 2963]}
,{"name":"amsterdam-2017-014", "size":[5184, 3456]}
,{"name":"amsterdam-2017-015", "size":[4777, 2778]}
,{"name":"amsterdam-2017-016", "size":[5184, 3456]}
,{"name":"amsterdam-2017-017", "size":[5184, 3456]}
,{"name":"amsterdam-2017-018", "size":[5184, 3456]}
,{"name":"amsterdam-2017-019", "size":[3456, 5184]}
,{"name":"amsterdam-2017-020", "size":[3456, 5184]}
,{"name":"amsterdam-2017-021", "size":[3456, 5184]}
,{"name":"amsterdam-2017-022", "size":[5177, 3198]}
,{"name":"amsterdam-2017-023", "size":[5002, 3456]}
,{"name":"amsterdam-2017-024", "size":[3456, 5184]}
,{"name":"amsterdam-2017-025", "size":[5184, 3456]}
,{"name":"amsterdam-2017-026", "size":[5184, 3456]}
,{"name":"amsterdam-2017-027", "size":[4879, 3456]}
,{"name":"amsterdam-2017-028", "size":[5184, 3456]}
,{"name":"amsterdam-2017-029", "size":[5184, 3456]}
,{"name":"amsterdam-2017-030", "size":[5184, 3456]}
,{"name":"amsterdam-2017-031", "size":[5184, 3456]}
,{"name":"amsterdam-2017-032", "size":[5184, 3456]}
,{"name":"amsterdam-2017-033", "size":[3456, 5184]}
,{"name":"amsterdam-2017-034", "size":[5184, 3456]}
,{"name":"amsterdam-2017-035", "size":[5184, 3456]}
,{"name":"amsterdam-2017-036", "size":[5184, 3456]}
,{"name":"amsterdam-2017-037", "size":[5184, 3456]}
,{"name":"amsterdam-2017-038", "size":[3456, 5184]}
,{"name":"amsterdam-2017-039", "size":[4851, 3456]}
,{"name":"amsterdam-2017-040", "size":[4012, 2904]}
,{"name":"amsterdam-2017-041", "size":[4803, 3253]}
,{"name":"amsterdam-2017-042", "size":[5184, 3456]}
,{"name":"amsterdam-2017-043", "size":[5184, 3456]}
,{"name":"amsterdam-2017-044", "size":[5184, 3456]}
,{"name":"amsterdam-2017-045", "size":[3358, 5048]}
,{"name":"amsterdam-2017-046", "size":[5184, 3456]}
,{"name":"amsterdam-2017-047", "size":[3456, 5184]}
,{"name":"amsterdam-2017-048", "size":[5184, 3456]}
,{"name":"amsterdam-2017-049", "size":[4698, 3132]}
,{"name":"amsterdam-2017-050", "size":[5184, 3456]}
,{"name":"amsterdam-2017-051", "size":[5184, 3456]}
,{"name":"amsterdam-2017-052", "size":[5184, 3456]}
,{"name":"amsterdam-2017-053", "size":[3456, 5184]}
,{"name":"amsterdam-2017-054", "size":[5184, 3456]}
,{"name":"amsterdam-2017-055", "size":[5184, 3456]}
,{"name":"amsterdam-2017-056", "size":[5184, 3456]}
,{"name":"amsterdam-2017-057", "size":[5184, 3456]}
,{"name":"amsterdam-2017-058", "size":[3456, 5184]}
,{"name":"amsterdam-2017-059", "size":[5184, 3456]}
,{"name":"amsterdam-2017-060", "size":[5184, 3456]}
,{"name":"amsterdam-2017-061", "size":[4143, 3295]}
,{"name":"amsterdam-2017-062", "size":[4730, 3160]}
,{"name":"amsterdam-2017-063", "size":[4542, 3254]}
]
}
